tergite_acl/__init__.py
tergite_acl/config/__init__.py
tergite_acl/config/settings.py
tergite_acl/experimental/__init__.py
tergite_acl/experimental/drag_amplitude.py
tergite_acl/experimental/time_of_flight.py
tergite_acl/functions/__init__.py
tergite_acl/functions/compilation_worker.py
tergite_acl/functions/execution_worker.py
tergite_acl/functions/monitor_worker.py
tergite_acl/functions/post_processing_worker.py
tergite_acl/lib/__init__.py
tergite_acl/lib/analysis/T1_analysis.py
tergite_acl/lib/analysis/__init__.py
tergite_acl/lib/analysis/check_cliffords_analysis.py
tergite_acl/lib/analysis/coupler_spectroscopy_analysis.py
tergite_acl/lib/analysis/cz_calibration_analysis.py
tergite_acl/lib/analysis/cz_chevron_analysis.py
tergite_acl/lib/analysis/cz_inspect.py
tergite_acl/lib/analysis/motzoi_analysis.py
tergite_acl/lib/analysis/n_rabi_analysis.py
tergite_acl/lib/analysis/optimum_ro_amplitude_analysis.py
tergite_acl/lib/analysis/optimum_ro_frequency_analysis.py
tergite_acl/lib/analysis/punchout_analysis.py
tergite_acl/lib/analysis/qubit_spectroscopy_analysis.py
tergite_acl/lib/analysis/qubit_spectroscopy_multidim.py
tergite_acl/lib/analysis/rabi_analysis.py
tergite_acl/lib/analysis/ramsey_analysis.py
tergite_acl/lib/analysis/randomized_benchmarking_analysis.py
tergite_acl/lib/analysis/resonator_spectroscopy_analysis.py
tergite_acl/lib/analysis/tof_analysis.py
tergite_acl/lib/analysis_base.py
tergite_acl/lib/calibration_schedules/T1.py
tergite_acl/lib/calibration_schedules/XY_crosstalk.py
tergite_acl/lib/calibration_schedules/__init__.py
tergite_acl/lib/calibration_schedules/check_cliffords.py
tergite_acl/lib/calibration_schedules/cz_calibration.py
tergite_acl/lib/calibration_schedules/cz_chevron.py
tergite_acl/lib/calibration_schedules/cz_chevron_reversed.py
tergite_acl/lib/calibration_schedules/motzoi_parameter.py
tergite_acl/lib/calibration_schedules/n_rabi_oscillations.py
tergite_acl/lib/calibration_schedules/punchout.py
tergite_acl-2024.2.0.dist-info/METADATA
tergite_acl-2024.2.0.dist-info/WHEEL
tergite_acl-2024.2.0.dist-info/entry_points.txt
tergite_acl-2024.2.0.dist-info/licenses/LICENSE.txt
tergite_acl-2024.2.0.dist-info/RECORD
