Metadata-Version: 2.4
Name: tergite-acl
Version: 2024.2.0
Summary: commandline application to calibrate QAL 9000-Like quantum computers automatically
License-File: LICENSE.txt
Author: Eleftherios Moschandreou
Author-email: elemos@chalmers.se
Requires-Python: >=3.9,<3.10
Classifier: Programming Language :: Python :: 3
Classifier: Programming Language :: Python :: 3.9
Requires-Dist: Jinja2 (==3.1.2)
Requires-Dist: click (==8.1.7)
Requires-Dist: colorama (==0.4.6)
Requires-Dist: h5netcdf (==1.0.2)
Requires-Dist: h5py (==3.7.0)
Requires-Dist: jokeapi (==1.0.5)
Requires-Dist: numpy (==1.25.2)
Requires-Dist: pyqt5-qt5 (==5.15.2) ; sys_platform == "linux"
Requires-Dist: pyqt5-qt5 (==5.15.2) ; sys_platform == "win32"
Requires-Dist: pyqt5-qt5 (>=5.15.2,<6.0.0) ; sys_platform == "darwin"
Requires-Dist: python-dotenv (==1.0.1)
Requires-Dist: qblox-instruments (==0.11.1)
Requires-Dist: qcodes (==0.39.1)
Requires-Dist: quantify-core (==0.7.3)
Requires-Dist: quantify-scheduler (==0.18.0)
Requires-Dist: redis (==5.0.0)
Requires-Dist: scikit-learn (==1.2.2)
Requires-Dist: toml (==0.10.2)
